odoo10_addon_purchase_request_analytic-10.0.1.1.0-nspkg.pth
odoo/addons/purchase_request_analytic/README.rst
odoo/addons/purchase_request_analytic/__init__.py
odoo/addons/purchase_request_analytic/__manifest__.py
odoo/addons/purchase_request_analytic/i18n/purchase_request_analytic.pot
odoo/addons/purchase_request_analytic/models/__init__.py
odoo/addons/purchase_request_analytic/models/purchase_request.py
odoo/addons/purchase_request_analytic/static/description/icon.png
odoo/addons/purchase_request_analytic/tests/__init__.py
odoo/addons/purchase_request_analytic/tests/test_purchase_request_analytic.py
odoo/addons/purchase_request_analytic/views/purchase_request_views.xml
odoo10_addon_purchase_request_analytic-10.0.1.1.0.dist-info/METADATA
odoo10_addon_purchase_request_analytic-10.0.1.1.0.dist-info/WHEEL
odoo10_addon_purchase_request_analytic-10.0.1.1.0.dist-info/namespace_packages.txt
odoo10_addon_purchase_request_analytic-10.0.1.1.0.dist-info/top_level.txt
odoo10_addon_purchase_request_analytic-10.0.1.1.0.dist-info/RECORD
